anydbx/__init__.py
anydbx/config.py
anydbx/manager.py
anydbx/pandas_io.py
anydbx-0.1.3.dist-info/METADATA
anydbx-0.1.3.dist-info/WHEEL
anydbx-0.1.3.dist-info/RECORD
